pallet_sim/__init__.py
pallet_sim/_load_example_data.py
pallet_sim/_mujocoviewer.py
pallet_sim/_order.py
pallet_sim/_pallet_visualizer.py
pallet_sim/gui_tool.py
pallet_sim/pallet_sim.py
pallet_sim/xml_obfuscator.py
pallet_sim/example_data/0615610.order.json
pallet_sim/example_data/0615611.order.json
pallet_sim/example_data/0615612.order.json
pallet_sim/example_data/0615613.order.json
pallet_sim/example_data/0615614.order.json
pallet_sim/example_data/0615615.order.json
pallet_sim/example_data/0615616.order.json
pallet_sim/example_data/0615617.order.json
pallet_sim/example_data/0615618.order.json
pallet_sim/example_data/0615619.order.json
pallet_sim/example_data/0615620.order.json
pallet_sim/example_data/0615621.order.json
pallet_sim/example_data/0615622.order.json
pallet_sim/example_data/0615623.order.json
pallet_sim/example_data/0615624.order.json
pallet_sim/example_data/0615625.order.json
pallet_sim/example_data/0615626.order.json
pallet_sim/example_data/0615627.order.json
pallet_sim/example_data/0615628.order.json
pallet_sim/example_data/0615629.order.json
pallet_sim/example_data/0615630.order.json
pallet_sim/example_data/0615631.order.json
pallet_sim/example_data/0615632.order.json
pallet_sim/example_data/0615633.order.json
pallet_sim/example_data/0615634.order.json
pallet_sim/example_data/0615635.order.json
pallet_sim/example_data/0615636.order.json
pallet_sim/example_data/0615637.order.json
pallet_sim/example_data/0615638.order.json
pallet_sim/example_data/0615639.order.json
pallet_sim/example_data/0615640.order.json
pallet_sim/example_data/0615641.order.json
pallet_sim/example_data/0615642.order.json
pallet_sim/example_data/0615643.order.json
pallet_sim/example_data/0615644.order.json
pallet_sim/example_data/0615645.order.json
pallet_sim/example_data/0615646.order.json
pallet_sim/example_data/0615647.order.json
pallet_sim/example_data/0615648.order.json
pallet_sim/example_data/0615649.order.json
pallet_sim/example_data/0615650.order.json
pallet_sim-0.0.22.dist-info/METADATA
pallet_sim-0.0.22.dist-info/WHEEL
pallet_sim-0.0.22.dist-info/top_level.txt
pallet_sim-0.0.22.dist-info/RECORD
