Metadata-Version: 2.1
Name: pallet-sim
Version: 0.0.22
Summary: Pallet simulation library developed at THWS
Author: Rodolfo Verde
Project-URL: GitLab, https://gitlab.com/rodolfo-verde/pallet-simulator
Classifier: License :: OSI Approved :: MIT License
Classifier: Programming Language :: Python :: 3
Requires-Dist: mujoco
Requires-Dist: pybullet
Requires-Dist: numpy-stl
Requires-Dist: mujoco-python-viewer
Requires-Dist: PyYAML
Requires-Dist: opencv-python
Requires-Dist: tqdm
Requires-Dist: ipywidgets
Requires-Dist: pyvista[all,trame]
